{"schema_version": 2, "corrections": [{"name": "jet_to_lep_fakerate", "description": "rates to estimate the contribution from jets that fake electrons", "version": 0, "inputs": [{"name": "id_wp_ele", "type": "string", "description": "Loose for no WP and iso and Tight for medium WP and iso<0.15"}, {"name": "pt", "type": "real", "description": "Reconstructed electron pT"}, {"name": "syst", "type": "string", "description": "Systematic variation: 'nom', 'up', 'down'"}], "output": {"name": "rate", "type": "real", "description": "pT-dependent rate"}, "data": {"nodetype": "category", "input": "id_wp_ele", "content": [{"key": "Tight", "value": {"nodetype": "binning", "input": "pt", "edges": [10.0, 15.0, 20.0, 30.0, 40.0, 60.0], "content": [{"nodetype": "category", "input": "syst", "content": [{"key": "syst_up", "value": 0.015772738141875704}, {"key": "syst_down", "value": 0.015977395031282527}, {"key": "stat_up", "value": 0.016112807981542007}, {"key": "stat_down", "value": 0.015637348626468796}, {"key": "nom", "value": 0.0158750783040054}]}, {"nodetype": "category", "input": "syst", "content": [{"key": "syst_up", "value": 0.013958205750863931}, {"key": "syst_down", "value": 0.014309611222129}, {"key": "stat_up", "value": 0.014481073790125941}, {"key": "stat_down", "value": 0.01378679265666221}, {"key": "nom", "value": 0.014133933223394075}]}, {"nodetype": "category", "input": "syst", "content": [{"key": "syst_up", "value": 0.012792328898082394}, {"key": "syst_down", "value": 0.013384624833353337}, {"key": "stat_up", "value": 0.01347576014469078}, {"key": "stat_down", "value": 0.012701293234476208}, {"key": "nom", "value": 0.013088526689583494}]}, {"nodetype": "category", "input": "syst", "content": [{"key": "syst_up", "value": 0.010276946530164768}, {"key": "syst_down", "value": 0.011522847946320533}, {"key": "stat_up", "value": 0.011585941472381876}, {"key": "stat_down", "value": 0.010214147747808808}, {"key": "nom", "value": 0.010900044610095342}]}, {"nodetype": "category", "input": "syst", "content": [{"key": "syst_up", "value": 0.009641250293330744}, {"key": "syst_down", "value": 0.012426664998686585}, {"key": "stat_up", "value": 0.012103016406876565}, {"key": "stat_down", "value": 0.009965793899261405}, {"key": "nom", "value": 0.011034405153068985}]}], "flow": "clamp"}}]}}]}